{
  "MP Stoinis": {
    "runs": 13,
    "balls": 6,
    "fours": 1,
    "sixes": 1,
    "outs": 0,
    "strikeRate": "216.67"
  },
  "AR Patel": {
    "runs": 26,
    "balls": 23,
    "fours": 3,
    "sixes": 0,
    "outs": 0,
    "strikeRate": "113.04"
  },
  "P Dubey": {
    "runs": 0,
    "balls": 0,
    "fours": 0,
    "sixes": 0,
    "outs": 0,
    "strikeRate": "0.00"
  },
  "R Ashwin": {
    "runs": 41,
    "balls": 26,
    "fours": 3,
    "sixes": 2,
    "outs": 0,
    "strikeRate": "157.69"
  },
  "K Rabada": {
    "runs": 19,
    "balls": 18,
    "fours": 1,
    "sixes": 1,
    "outs": 0,
    "strikeRate": "105.56"
  },
  "A Nortje": {
    "runs": 17,
    "balls": 12,
    "fours": 4,
    "sixes": 0,
    "outs": 0,
    "strikeRate": "141.67"
  },
  "DR Sams": {
    "runs": 6,
    "balls": 5,
    "fours": 1,
    "sixes": 0,
    "outs": 0,
    "strikeRate": "120.00"
  },
  "I Udana": {
    "runs": 0,
    "balls": 0,
    "fours": 0,
    "sixes": 0,
    "outs": 0,
    "strikeRate": "0.00"
  },
  "JC Archer": {
    "runs": 0,
    "balls": 0,
    "fours": 0,
    "sixes": 0,
    "outs": 0,
    "strikeRate": "0.00"
  },
  "AS Rajpoot": {
    "runs": 0,
    "balls": 0,
    "fours": 0,
    "sixes": 0,
    "outs": 0,
    "strikeRate": "0.00"
  },
  "Kartik Tyagi": {
    "runs": 30,
    "balls": 19,
    "fours": 5,
    "sixes": 0,
    "outs": 0,
    "strikeRate": "157.89"
  },
  "S Gopal": {
    "runs": 29,
    "balls": 17,
    "fours": 5,
    "sixes": 0,
    "outs": 0,
    "strikeRate": "170.59"
  },
  "R Tewatia": {
    "runs": 11,
    "balls": 12,
    "fours": 0,
    "sixes": 0,
    "outs": 0,
    "strikeRate": "91.67"
  },
  "Sandeep Sharma": {
    "runs": 9,
    "balls": 8,
    "fours": 2,
    "sixes": 0,
    "outs": 0,
    "strikeRate": "112.50"
  },
  "T Natarajan": {
    "runs": 5,
    "balls": 11,
    "fours": 0,
    "sixes": 0,
    "outs": 0,
    "strikeRate": "45.45"
  },
  "S Kaul": {
    "runs": 21,
    "balls": 8,
    "fours": 5,
    "sixes": 0,
    "outs": 0,
    "strikeRate": "262.50"
  },
  "HV Patel": {
    "runs": 8,
    "balls": 5,
    "fours": 1,
    "sixes": 0,
    "outs": 0,
    "strikeRate": "160.00"
  },
  "Shivam Mavi": {
    "runs": 7,
    "balls": 8,
    "fours": 1,
    "sixes": 0,
    "outs": 0,
    "strikeRate": "87.50"
  },
  "CV Varun": {
    "runs": 5,
    "balls": 4,
    "fours": 0,
    "sixes": 0,
    "outs": 0,
    "strikeRate": "125.00"
  },
  "Arshdeep Singh": {
    "runs": 0,
    "balls": 1,
    "fours": 0,
    "sixes": 0,
    "outs": 0,
    "strikeRate": "0.00"
  },
  "Mohammed Shami": {
    "runs": 0,
    "balls": 3,
    "fours": 0,
    "sixes": 0,
    "outs": 0,
    "strikeRate": "0.00"
  },
  "TK Curran": {
    "runs": 0,
    "balls": 0,
    "fours": 0,
    "sixes": 0,
    "outs": 0,
    "strikeRate": "0.00"
  },
  "S Sandeep Warrier": {
    "runs": 0,
    "balls": 0,
    "fours": 0,
    "sixes": 0,
    "outs": 0,
    "strikeRate": "0.00"
  },
  "PJ Cummins": {
    "runs": 1,
    "balls": 1,
    "fours": 0,
    "sixes": 0,
    "outs": 0,
    "strikeRate": "100.00"
  },
  "SP Narine": {
    "runs": 0,
    "balls": 0,
    "fours": 0,
    "sixes": 0,
    "outs": 0,
    "strikeRate": "0.00"
  },
  "AD Russell": {
    "runs": 1,
    "balls": 1,
    "fours": 0,
    "sixes": 0,
    "outs": 0,
    "strikeRate": "100.00"
  },
  "Kuldeep Yadav": {
    "runs": 12,
    "balls": 8,
    "fours": 0,
    "sixes": 1,
    "outs": 0,
    "strikeRate": "150.00"
  },
  "SS Cottrell": {
    "runs": 0,
    "balls": 0,
    "fours": 0,
    "sixes": 0,
    "outs": 0,
    "strikeRate": "0.00"
  },
  "Ravi Bishnoi": {
    "runs": 1,
    "balls": 1,
    "fours": 0,
    "sixes": 0,
    "outs": 0,
    "strikeRate": "100.00"
  },
  "Mohammed Siraj": {
    "runs": 20,
    "balls": 10,
    "fours": 4,
    "sixes": 0,
    "outs": 0,
    "strikeRate": "200.00"
  },
  "Washington Sundar": {
    "runs": 5,
    "balls": 7,
    "fours": 0,
    "sixes": 0,
    "outs": 0,
    "strikeRate": "71.43"
  },
  "YS Chahal": {
    "runs": 25,
    "balls": 13,
    "fours": 2,
    "sixes": 2,
    "outs": 0,
    "strikeRate": "192.31"
  },
  "DW Steyn": {
    "runs": 0,
    "balls": 0,
    "fours": 0,
    "sixes": 0,
    "outs": 0,
    "strikeRate": "0.00"
  },
  "CH Morris": {
    "runs": 0,
    "balls": 0,
    "fours": 0,
    "sixes": 0,
    "outs": 0,
    "strikeRate": "0.00"
  },
  "JO Holder": {
    "runs": 6,
    "balls": 5,
    "fours": 1,
    "sixes": 0,
    "outs": 0,
    "strikeRate": "120.00"
  },
  "S Nadeem": {
    "runs": 0,
    "balls": 0,
    "fours": 0,
    "sixes": 0,
    "outs": 0,
    "strikeRate": "0.00"
  },
  "Rashid Khan": {
    "runs": 10,
    "balls": 7,
    "fours": 1,
    "sixes": 0,
    "outs": 0,
    "strikeRate": "142.86"
  },
  "PP Chawla": {
    "runs": 0,
    "balls": 0,
    "fours": 0,
    "sixes": 0,
    "outs": 0,
    "strikeRate": "0.00"
  },
  "SM Curran": {
    "runs": 0,
    "balls": 0,
    "fours": 0,
    "sixes": 0,
    "outs": 0,
    "strikeRate": "0.00"
  },
  "RA Jadeja": {
    "runs": 8,
    "balls": 5,
    "fours": 1,
    "sixes": 0,
    "outs": 0,
    "strikeRate": "160.00"
  },
  "DL Chahar": {
    "runs": 0,
    "balls": 0,
    "fours": 0,
    "sixes": 0,
    "outs": 0,
    "strikeRate": "0.00"
  }
}